ediel/__init__.py
ediel/filename.py
ediel/mig.py
ediel/misc.py
ediel/twowire.py
ediel/uniformat.py
ediel-0.0.34.dist-info/licenses/LICENSE
ediel-0.0.34.dist-info/METADATA
ediel-0.0.34.dist-info/WHEEL
ediel-0.0.34.dist-info/top_level.txt
ediel-0.0.34.dist-info/RECORD
